CHANGES.rst
CONTRIBUTORS.rst
DEVELOP.rst
LICENSE.rst
MANIFEST.in
README.rst
setup.cfg
setup.py
docs/conf.py
docs/index.rst
src/acentoweb/.DS_Store
src/acentoweb/__init__.py
src/acentoweb.ecv.egg-info/PKG-INFO
src/acentoweb.ecv.egg-info/SOURCES.txt
src/acentoweb.ecv.egg-info/dependency_links.txt
src/acentoweb.ecv.egg-info/entry_points.txt
src/acentoweb.ecv.egg-info/namespace_packages.txt
src/acentoweb.ecv.egg-info/not-zip-safe
src/acentoweb.ecv.egg-info/requires.txt
src/acentoweb.ecv.egg-info/top_level.txt
src/acentoweb/ecv/.DS_Store
src/acentoweb/ecv/__init__.py
src/acentoweb/ecv/configure.zcml
src/acentoweb/ecv/interfaces.py
src/acentoweb/ecv/permissions.zcml
src/acentoweb/ecv/setuphandlers.py
src/acentoweb/ecv/testing.py
src/acentoweb/ecv/browser/.DS_Store
src/acentoweb/ecv/browser/__init__.py
src/acentoweb/ecv/browser/configure.zcml
src/acentoweb/ecv/browser/overrides/.gitkeep
src/acentoweb/ecv/browser/static/.gitkeep
src/acentoweb/ecv/locales/.DS_Store
src/acentoweb/ecv/locales/README.rst
src/acentoweb/ecv/locales/__init__.py
src/acentoweb/ecv/locales/acentoweb.ecv.pot
src/acentoweb/ecv/locales/update.py
src/acentoweb/ecv/locales/update.sh
src/acentoweb/ecv/locales/en/.DS_Store
src/acentoweb/ecv/locales/en/LC_MESSAGES/acentoweb.ecv.mo
src/acentoweb/ecv/locales/en/LC_MESSAGES/acentoweb.ecv.po
src/acentoweb/ecv/profiles/.DS_Store
src/acentoweb/ecv/profiles/default/actions.xml
src/acentoweb/ecv/profiles/default/browserlayer.xml
src/acentoweb/ecv/profiles/default/catalog.xml
src/acentoweb/ecv/profiles/default/metadata.xml
src/acentoweb/ecv/profiles/default/registry.xml
src/acentoweb/ecv/profiles/uninstall/actions.xml
src/acentoweb/ecv/profiles/uninstall/browserlayer.xml
src/acentoweb/ecv/tests/__init__.py
src/acentoweb/ecv/tests/test_robot.py
src/acentoweb/ecv/tests/test_setup.py
src/acentoweb/ecv/tests/test_view_ecv_view.py
src/acentoweb/ecv/tests/robot/test_example.robot
src/acentoweb/ecv/views/__init__.py
src/acentoweb/ecv/views/configure.zcml
src/acentoweb/ecv/views/ecv.pt
src/acentoweb/ecv/views/ecv_view-kopi.pt
src/acentoweb/ecv/views/ecv_view.py
src/acentoweb/ecv/views/lexicon.py
src/acentoweb/ecv/views/test.ecv