Metadata-Version: 1.2
Name: acentoweb.ecv
Version: 1.4.6
Summary: CVE export function for Plone
Home-page: https://github.com/collective/acentoweb.ecv
Author: Espen Moe-Nilssen
Author-email: espen@medialog.no
License: GPL version 2
Project-URL: Source, https://github.com/espenmn/acentoweb.ecv
Project-URL: Tracker, https://github.com/espenmn/acentoweb.ecv/issues
Project-URL: PyPI, https://pypi.python.org/pypi/acentoweb.ecv
Keywords: Python Plone
Platform: UNKNOWN
Classifier: Environment :: Web Environment
Classifier: Framework :: Plone
Classifier: Framework :: Plone :: Addon
Classifier: Framework :: Plone :: 5.1
Classifier: Programming Language :: Python
Classifier: Programming Language :: Python :: 2.7
Classifier: Operating System :: OS Independent
Classifier: License :: OSI Approved :: GNU General Public License v2 (GPLv2)
Requires-Python: ==2.7
